{
    "1": {
        "loss": 0.0426,
        "timesteps": 3,
        "average_reward": 0.0,
        "duration": 1.46
    },
    "2": {
        "loss": 0.0064,
        "timesteps": 3,
        "average_reward": 0.0,
        "duration": 1.32
    },
    "3": {
        "loss": 0.0104,
        "timesteps": 3,
        "average_reward": 0.0,
        "duration": 1.04
    },
    "4": {
        "loss": 0.0132,
        "timesteps": 3,
        "average_reward": 0.0,
        "duration": 1.1
    },
    "5": {
        "loss": 0.0065,
        "timesteps": 3,
        "average_reward": 0.0,
        "duration": 1.02
    },
    "6": {
        "loss": 0.0074,
        "timesteps": 3,
        "average_reward": 0.0,
        "duration": 1.02
    },
    "7": {
        "loss": 0.0069,
        "timesteps": 3,
        "average_reward": 0.0,
        "duration": 1.11
    },
    "8": {
        "loss": 0.016,
        "timesteps": 3,
        "average_reward": 0.0,
        "duration": 1.15
    },
    "9": {
        "loss": 0.0131,
        "timesteps": 4,
        "average_reward": 0.0,
        "duration": 4.35
    },
    "10": {
        "loss": 0.0157,
        "timesteps": 3,
        "average_reward": 0.0,
        "duration": 0.99
    },
    "11": {
        "loss": 0.0173,
        "timesteps": 3,
        "average_reward": 0.0,
        "duration": 0.94
    },
    "12": {
        "loss": 0.0174,
        "timesteps": 3,
        "average_reward": 0.0,
        "duration": 1.12
    },
    "13": {
        "loss": 0.0166,
        "timesteps": 3,
        "average_reward": 0.0,
        "duration": 0.87
    },
    "14": {
        "loss": 0.0199,
        "timesteps": 4,
        "average_reward": 0.0,
        "duration": 1.62
    },
    "15": {
        "loss": 0.0147,
        "timesteps": 4,
        "average_reward": 0.0,
        "duration": 1.65
    },
    "16": {
        "loss": 0.0193,
        "timesteps": 4,
        "average_reward": 0.0,
        "duration": 2.41
    },
    "17": {
        "loss": 0.0175,
        "timesteps": 4,
        "average_reward": 0.0,
        "duration": 1.55
    },
    "18": {
        "loss": 0.017,
        "timesteps": 3,
        "average_reward": 0.0,
        "duration": 1.08
    },
    "19": {
        "loss": 0.0168,
        "timesteps": 3,
        "average_reward": 0.0,
        "duration": 0.89
    },
    "20": {
        "loss": 0.0186,
        "timesteps": 3,
        "average_reward": 0.0,
        "duration": 1.13
    },
    "21": {
        "loss": 0.0168,
        "timesteps": 3,
        "average_reward": 0.0,
        "duration": 1.01
    },
    "22": {
        "loss": 0.017,
        "timesteps": 3,
        "average_reward": 0.0,
        "duration": 4.06
    },
    "23": {
        "loss": 0.0153,
        "timesteps": 3,
        "average_reward": 0.0,
        "duration": 0.97
    },
    "24": {
        "loss": 0.015,
        "timesteps": 3,
        "average_reward": 0.0,
        "duration": 3.89
    },
    "25": {
        "loss": 0.017,
        "timesteps": 3,
        "average_reward": 0.0,
        "duration": 1.1
    },
    "26": {
        "loss": 0.0154,
        "timesteps": 4,
        "average_reward": 0.0,
        "duration": 4.57
    },
    "27": {
        "loss": 0.0174,
        "timesteps": 3,
        "average_reward": 0.0,
        "duration": 1.96
    },
    "28": {
        "loss": 0.0177,
        "timesteps": 3,
        "average_reward": 0.0,
        "duration": 4.04
    },
    "29": {
        "loss": 0.0152,
        "timesteps": 3,
        "average_reward": 0.0,
        "duration": 1.06
    },
    "30": {
        "loss": 0.0169,
        "timesteps": 3,
        "average_reward": 0.0,
        "duration": 1.81
    },
    "31": {
        "loss": 0.0175,
        "timesteps": 3,
        "average_reward": 0.0,
        "duration": 1.87
    },
    "32": {
        "loss": 0.0185,
        "timesteps": 4,
        "average_reward": 0.0,
        "duration": 4.6
    },
    "33": {
        "loss": 0.0138,
        "timesteps": 3,
        "average_reward": 0.0,
        "duration": 0.99
    },
    "34": {
        "loss": 0.0168,
        "timesteps": 3,
        "average_reward": 0.0,
        "duration": 1.18
    },
    "35": {
        "loss": 0.017,
        "timesteps": 3,
        "average_reward": 0.0,
        "duration": 0.97
    },
    "36": {
        "loss": 0.0165,
        "timesteps": 4,
        "average_reward": 0.0,
        "duration": 1.62
    },
    "37": {
        "loss": 0.0161,
        "timesteps": 4,
        "average_reward": 0.0,
        "duration": 1.45
    },
    "38": {
        "loss": 0.0219,
        "timesteps": 3,
        "average_reward": 0.0,
        "duration": 1.21
    },
    "39": {
        "loss": 0.0147,
        "timesteps": 3,
        "average_reward": 0.0,
        "duration": 0.92
    },
    "40": {
        "loss": 0.0159,
        "timesteps": 3,
        "average_reward": 0.0,
        "duration": 1.0
    },
    "41": {
        "loss": 0.0151,
        "timesteps": 3,
        "average_reward": 0.0,
        "duration": 0.92
    },
    "42": {
        "loss": 0.0133,
        "timesteps": 3,
        "average_reward": 0.0,
        "duration": 0.97
    },
    "43": {
        "loss": 0.0154,
        "timesteps": 3,
        "average_reward": 0.0,
        "duration": 1.83
    },
    "44": {
        "loss": 0.0121,
        "timesteps": 4,
        "average_reward": 0.0,
        "duration": 4.5
    },
    "45": {
        "loss": 0.013,
        "timesteps": 3,
        "average_reward": 0.0,
        "duration": 4.62
    },
    "46": {
        "loss": 0.0162,
        "timesteps": 3,
        "average_reward": 0.0,
        "duration": 1.1
    },
    "47": {
        "loss": 0.0145,
        "timesteps": 3,
        "average_reward": 0.0,
        "duration": 4.08
    },
    "48": {
        "loss": 0.0176,
        "timesteps": 3,
        "average_reward": 0.0,
        "duration": 0.97
    },
    "49": {
        "loss": 0.0176,
        "timesteps": 4,
        "average_reward": 0.0,
        "duration": 1.61
    },
    "50": {
        "loss": 0.0163,
        "timesteps": 3,
        "average_reward": 0.0,
        "duration": 3.85
    },
    "51": {
        "loss": 0.0155,
        "timesteps": 3,
        "average_reward": 0.0,
        "duration": 0.98
    },
    "52": {
        "loss": 0.0169,
        "timesteps": 3,
        "average_reward": 0.0,
        "duration": 1.19
    },
    "53": {
        "loss": 0.0172,
        "timesteps": 3,
        "average_reward": 0.0,
        "duration": 4.13
    },
    "54": {
        "loss": 0.0169,
        "timesteps": 3,
        "average_reward": 0.0,
        "duration": 1.17
    },
    "55": {
        "loss": 0.0176,
        "timesteps": 3,
        "average_reward": 0.0,
        "duration": 0.95
    },
    "56": {
        "loss": 0.0201,
        "timesteps": 4,
        "average_reward": 0.0,
        "duration": 1.61
    },
    "57": {
        "loss": 0.0166,
        "timesteps": 3,
        "average_reward": 0.0,
        "duration": 4.18
    },
    "58": {
        "loss": 0.0187,
        "timesteps": 4,
        "average_reward": 0.0,
        "duration": 1.53
    },
    "59": {
        "loss": 0.0146,
        "timesteps": 3,
        "average_reward": 0.0,
        "duration": 3.92
    },
    "60": {
        "loss": 0.0142,
        "timesteps": 4,
        "average_reward": 0.0,
        "duration": 2.32
    },
    "61": {
        "loss": 0.0155,
        "timesteps": 3,
        "average_reward": 0.0,
        "duration": 3.89
    },
    "62": {
        "loss": 0.0165,
        "timesteps": 3,
        "average_reward": 0.0,
        "duration": 3.83
    },
    "63": {
        "loss": 0.0132,
        "timesteps": 4,
        "average_reward": 0.0,
        "duration": 1.54
    },
    "64": {
        "loss": 0.0127,
        "timesteps": 3,
        "average_reward": 0.0,
        "duration": 4.01
    },
    "65": {
        "loss": 0.0133,
        "timesteps": 3,
        "average_reward": 0.0,
        "duration": 3.98
    },
    "66": {
        "loss": 0.0149,
        "timesteps": 3,
        "average_reward": 0.0,
        "duration": 3.99
    },
    "67": {
        "loss": 0.0156,
        "timesteps": 3,
        "average_reward": 0.0,
        "duration": 4.47
    },
    "68": {
        "loss": 0.0156,
        "timesteps": 4,
        "average_reward": 0.0,
        "duration": 4.36
    },
    "69": {
        "loss": 0.0154,
        "timesteps": 3,
        "average_reward": 0.0,
        "duration": 0.91
    },
    "70": {
        "loss": 0.0166,
        "timesteps": 3,
        "average_reward": 0.0,
        "duration": 1.86
    },
    "71": {
        "loss": 0.0128,
        "timesteps": 3,
        "average_reward": 0.0,
        "duration": 4.01
    },
    "72": {
        "loss": 0.0127,
        "timesteps": 3,
        "average_reward": 0.0,
        "duration": 0.93
    },
    "73": {
        "loss": 0.0137,
        "timesteps": 3,
        "average_reward": 0.0,
        "duration": 1.0
    },
    "74": {
        "loss": 0.0124,
        "timesteps": 3,
        "average_reward": 0.0,
        "duration": 1.66
    },
    "75": {
        "loss": 0.0153,
        "timesteps": 3,
        "average_reward": 0.0,
        "duration": 4.89
    },
    "76": {
        "loss": 0.0109,
        "timesteps": 4,
        "average_reward": 0.0,
        "duration": 5.06
    },
    "77": {
        "loss": 0.0129,
        "timesteps": 3,
        "average_reward": 0.0,
        "duration": 3.79
    },
    "78": {
        "loss": 0.0144,
        "timesteps": 3,
        "average_reward": 0.0,
        "duration": 1.1
    },
    "79": {
        "loss": 0.0152,
        "timesteps": 3,
        "average_reward": 0.0,
        "duration": 3.87
    },
    "80": {
        "loss": 0.0131,
        "timesteps": 3,
        "average_reward": 0.0,
        "duration": 1.81
    },
    "81": {
        "loss": 0.0126,
        "timesteps": 3,
        "average_reward": 0.0,
        "duration": 3.93
    },
    "82": {
        "loss": 0.0168,
        "timesteps": 3,
        "average_reward": 0.0,
        "duration": 1.07
    },
    "83": {
        "loss": 0.0141,
        "timesteps": 3,
        "average_reward": 0.0,
        "duration": 1.03
    },
    "84": {
        "loss": 0.0154,
        "timesteps": 3,
        "average_reward": 0.0,
        "duration": 3.87
    },
    "85": {
        "loss": 0.015,
        "timesteps": 3,
        "average_reward": 0.0,
        "duration": 4.3
    },
    "86": {
        "loss": 0.0133,
        "timesteps": 3,
        "average_reward": 0.0,
        "duration": 1.07
    },
    "87": {
        "loss": 0.0153,
        "timesteps": 3,
        "average_reward": 0.0,
        "duration": 1.01
    },
    "88": {
        "loss": 0.011,
        "timesteps": 4,
        "average_reward": 0.0,
        "duration": 4.43
    },
    "89": {
        "loss": 0.0115,
        "timesteps": 3,
        "average_reward": 0.0,
        "duration": 3.77
    },
    "90": {
        "loss": 0.0089,
        "timesteps": 3,
        "average_reward": 0.0,
        "duration": 3.91
    },
    "91": {
        "loss": 0.0108,
        "timesteps": 3,
        "average_reward": 0.0,
        "duration": 1.77
    },
    "92": {
        "loss": 0.0112,
        "timesteps": 3,
        "average_reward": 0.0,
        "duration": 1.72
    },
    "93": {
        "loss": 0.0105,
        "timesteps": 3,
        "average_reward": 0.0,
        "duration": 4.37
    },
    "94": {
        "loss": 0.0109,
        "timesteps": 3,
        "average_reward": 0.0,
        "duration": 4.28
    },
    "95": {
        "loss": 0.0109,
        "timesteps": 3,
        "average_reward": 0.0,
        "duration": 0.97
    },
    "96": {
        "loss": 0.0092,
        "timesteps": 3,
        "average_reward": 0.0,
        "duration": 4.43
    },
    "97": {
        "loss": 0.0096,
        "timesteps": 3,
        "average_reward": 0.0,
        "duration": 1.88
    },
    "98": {
        "loss": 0.0092,
        "timesteps": 3,
        "average_reward": 0.0,
        "duration": 1.08
    },
    "99": {
        "loss": 0.0094,
        "timesteps": 3,
        "average_reward": 0.0,
        "duration": 1.04
    },
    "100": {
        "loss": 0.0116,
        "timesteps": 4,
        "average_reward": 0.0,
        "duration": 1.49
    },
    "101": {
        "loss": 0.0127,
        "timesteps": 3,
        "average_reward": 0.0,
        "duration": 4.13
    },
    "102": {
        "loss": 0.0119,
        "timesteps": 3,
        "average_reward": 0.0,
        "duration": 4.04
    },
    "103": {
        "loss": 0.0112,
        "timesteps": 3,
        "average_reward": 0.0,
        "duration": 1.08
    },
    "104": {
        "loss": 0.0131,
        "timesteps": 3,
        "average_reward": 0.0,
        "duration": 1.11
    },
    "105": {
        "loss": 0.014,
        "timesteps": 3,
        "average_reward": 0.0,
        "duration": 3.76
    },
    "106": {
        "loss": 0.0081,
        "timesteps": 4,
        "average_reward": 0.0,
        "duration": 1.53
    },
    "107": {
        "loss": 0.01,
        "timesteps": 3,
        "average_reward": 0.0,
        "duration": 3.83
    },
    "108": {
        "loss": 0.0089,
        "timesteps": 3,
        "average_reward": 0.0,
        "duration": 4.18
    },
    "109": {
        "loss": 0.0074,
        "timesteps": 3,
        "average_reward": 0.0,
        "duration": 4.06
    },
    "110": {
        "loss": 0.0075,
        "timesteps": 3,
        "average_reward": 0.0,
        "duration": 4.15
    },
    "111": {
        "loss": 0.0105,
        "timesteps": 3,
        "average_reward": 0.0,
        "duration": 3.98
    },
    "112": {
        "loss": 0.011,
        "timesteps": 3,
        "average_reward": 0.0,
        "duration": 4.76
    },
    "113": {
        "loss": 0.0086,
        "timesteps": 3,
        "average_reward": 0.0,
        "duration": 3.99
    },
    "114": {
        "loss": 0.0102,
        "timesteps": 3,
        "average_reward": 0.0,
        "duration": 4.22
    },
    "115": {
        "loss": 0.0086,
        "timesteps": 3,
        "average_reward": 0.0,
        "duration": 4.13
    },
    "116": {
        "loss": 0.0131,
        "timesteps": 3,
        "average_reward": 0.0,
        "duration": 4.9
    },
    "117": {
        "loss": 0.0119,
        "timesteps": 3,
        "average_reward": 0.0,
        "duration": 4.14
    },
    "118": {
        "loss": 0.009,
        "timesteps": 3,
        "average_reward": 0.0,
        "duration": 4.15
    },
    "119": {
        "loss": 0.0083,
        "timesteps": 3,
        "average_reward": 0.0,
        "duration": 0.89
    },
    "120": {
        "loss": 0.0098,
        "timesteps": 3,
        "average_reward": 0.0,
        "duration": 4.86
    },
    "121": {
        "loss": 0.0097,
        "timesteps": 3,
        "average_reward": 0.0,
        "duration": 4.63
    },
    "122": {
        "loss": 0.0083,
        "timesteps": 3,
        "average_reward": 0.0,
        "duration": 4.03
    },
    "123": {
        "loss": 0.0072,
        "timesteps": 3,
        "average_reward": 0.0,
        "duration": 4.36
    },
    "124": {
        "loss": 0.0091,
        "timesteps": 3,
        "average_reward": 0.0,
        "duration": 4.22
    },
    "125": {
        "loss": 0.0125,
        "timesteps": 3,
        "average_reward": 0.0,
        "duration": 4.57
    },
    "126": {
        "loss": 0.0095,
        "timesteps": 3,
        "average_reward": 0.0,
        "duration": 4.17
    },
    "127": {
        "loss": 0.0107,
        "timesteps": 3,
        "average_reward": 0.0,
        "duration": 4.04
    },
    "128": {
        "loss": 0.0108,
        "timesteps": 4,
        "average_reward": 0.0,
        "duration": 2.44
    },
    "129": {
        "loss": 0.0102,
        "timesteps": 3,
        "average_reward": 0.0,
        "duration": 4.45
    },
    "130": {
        "loss": 0.0073,
        "timesteps": 3,
        "average_reward": 0.0,
        "duration": 4.21
    },
    "131": {
        "loss": 0.01,
        "timesteps": 3,
        "average_reward": 0.0,
        "duration": 4.01
    },
    "132": {
        "loss": 0.0107,
        "timesteps": 3,
        "average_reward": 0.0,
        "duration": 1.9
    },
    "133": {
        "loss": 0.0084,
        "timesteps": 3,
        "average_reward": 0.0,
        "duration": 1.8
    },
    "134": {
        "loss": 0.0072,
        "timesteps": 3,
        "average_reward": 0.0,
        "duration": 4.13
    },
    "135": {
        "loss": 0.0081,
        "timesteps": 3,
        "average_reward": 0.0,
        "duration": 4.01
    },
    "136": {
        "loss": 0.0082,
        "timesteps": 3,
        "average_reward": 0.0,
        "duration": 3.99
    },
    "137": {
        "loss": 0.0086,
        "timesteps": 3,
        "average_reward": 0.0,
        "duration": 4.63
    },
    "138": {
        "loss": 0.0076,
        "timesteps": 3,
        "average_reward": 0.0,
        "duration": 4.4
    },
    "139": {
        "loss": 0.0082,
        "timesteps": 3,
        "average_reward": 0.0,
        "duration": 4.49
    },
    "140": {
        "loss": 0.0081,
        "timesteps": 3,
        "average_reward": 0.0,
        "duration": 4.4
    },
    "141": {
        "loss": 0.0091,
        "timesteps": 3,
        "average_reward": 0.0,
        "duration": 4.44
    },
    "142": {
        "loss": 0.0107,
        "timesteps": 3,
        "average_reward": 0.0,
        "duration": 4.62
    },
    "143": {
        "loss": 0.0087,
        "timesteps": 3,
        "average_reward": 0.0,
        "duration": 3.95
    },
    "144": {
        "loss": 0.0071,
        "timesteps": 3,
        "average_reward": 0.0,
        "duration": 4.31
    },
    "145": {
        "loss": 0.0086,
        "timesteps": 3,
        "average_reward": 0.0,
        "duration": 1.8
    },
    "146": {
        "loss": 0.0099,
        "timesteps": 3,
        "average_reward": 0.0,
        "duration": 0.98
    },
    "147": {
        "loss": 0.0071,
        "timesteps": 3,
        "average_reward": 0.0,
        "duration": 4.6
    },
    "148": {
        "loss": 0.0089,
        "timesteps": 3,
        "average_reward": 0.0,
        "duration": 1.82
    },
    "149": {
        "loss": 0.0093,
        "timesteps": 3,
        "average_reward": 0.0,
        "duration": 4.13
    },
    "150": {
        "loss": 0.0095,
        "timesteps": 3,
        "average_reward": 0.0,
        "duration": 4.55
    },
    "151": {
        "loss": 0.0097,
        "timesteps": 3,
        "average_reward": 0.0,
        "duration": 3.96
    },
    "152": {
        "loss": 0.0077,
        "timesteps": 3,
        "average_reward": 0.0,
        "duration": 4.58
    },
    "153": {
        "loss": 0.0088,
        "timesteps": 3,
        "average_reward": 0.0,
        "duration": 4.01
    },
    "154": {
        "loss": 0.0078,
        "timesteps": 3,
        "average_reward": 0.0,
        "duration": 4.26
    },
    "155": {
        "loss": 0.0104,
        "timesteps": 3,
        "average_reward": 0.0,
        "duration": 4.39
    },
    "156": {
        "loss": 0.0088,
        "timesteps": 3,
        "average_reward": 0.0,
        "duration": 4.1
    },
    "157": {
        "loss": 0.0075,
        "timesteps": 3,
        "average_reward": 0.0,
        "duration": 3.94
    },
    "158": {
        "loss": 0.0075,
        "timesteps": 3,
        "average_reward": 0.0,
        "duration": 4.29
    },
    "159": {
        "loss": 0.0061,
        "timesteps": 3,
        "average_reward": 0.0,
        "duration": 3.87
    },
    "160": {
        "loss": 0.0064,
        "timesteps": 3,
        "average_reward": 0.0,
        "duration": 4.34
    },
    "161": {
        "loss": 0.0081,
        "timesteps": 3,
        "average_reward": 0.0,
        "duration": 3.93
    },
    "162": {
        "loss": 0.0057,
        "timesteps": 3,
        "average_reward": 0.0,
        "duration": 4.28
    },
    "163": {
        "loss": 0.0079,
        "timesteps": 3,
        "average_reward": 0.0,
        "duration": 4.25
    },
    "164": {
        "loss": 0.0076,
        "timesteps": 3,
        "average_reward": 0.0,
        "duration": 3.64
    },
    "165": {
        "loss": 0.0073,
        "timesteps": 3,
        "average_reward": 0.0,
        "duration": 4.26
    },
    "166": {
        "loss": 0.0063,
        "timesteps": 3,
        "average_reward": 0.0,
        "duration": 3.81
    },
    "167": {
        "loss": 0.0073,
        "timesteps": 3,
        "average_reward": 0.0,
        "duration": 3.7
    },
    "168": {
        "loss": 0.0085,
        "timesteps": 3,
        "average_reward": 0.0,
        "duration": 3.62
    },
    "169": {
        "loss": 0.0069,
        "timesteps": 3,
        "average_reward": 0.0,
        "duration": 4.13
    },
    "170": {
        "loss": 0.0067,
        "timesteps": 3,
        "average_reward": 0.0,
        "duration": 4.06
    },
    "171": {
        "loss": 0.0067,
        "timesteps": 3,
        "average_reward": 0.0,
        "duration": 3.72
    },
    "172": {
        "loss": 0.0062,
        "timesteps": 3,
        "average_reward": 0.0,
        "duration": 3.71
    },
    "173": {
        "loss": 0.0085,
        "timesteps": 3,
        "average_reward": 0.0,
        "duration": 4.3
    },
    "174": {
        "loss": 0.0062,
        "timesteps": 3,
        "average_reward": 0.0,
        "duration": 4.31
    },
    "175": {
        "loss": 0.0064,
        "timesteps": 3,
        "average_reward": 0.0,
        "duration": 4.17
    },
    "176": {
        "loss": 0.0056,
        "timesteps": 3,
        "average_reward": 0.0,
        "duration": 4.16
    },
    "177": {
        "loss": 0.0069,
        "timesteps": 3,
        "average_reward": 0.0,
        "duration": 4.37
    },
    "178": {
        "loss": 0.0071,
        "timesteps": 3,
        "average_reward": 0.0,
        "duration": 4.1
    },
    "179": {
        "loss": 0.0079,
        "timesteps": 3,
        "average_reward": 0.0,
        "duration": 3.81
    },
    "180": {
        "loss": 0.0079,
        "timesteps": 3,
        "average_reward": 0.0,
        "duration": 4.25
    },
    "181": {
        "loss": 0.0067,
        "timesteps": 3,
        "average_reward": 0.0,
        "duration": 3.96
    },
    "182": {
        "loss": 0.0055,
        "timesteps": 3,
        "average_reward": 0.0,
        "duration": 4.02
    },
    "183": {
        "loss": 0.0075,
        "timesteps": 3,
        "average_reward": 0.0,
        "duration": 1.66
    },
    "184": {
        "loss": 0.0056,
        "timesteps": 3,
        "average_reward": 0.0,
        "duration": 4.05
    },
    "185": {
        "loss": 0.0082,
        "timesteps": 3,
        "average_reward": 0.0,
        "duration": 3.61
    },
    "186": {
        "loss": 0.0064,
        "timesteps": 3,
        "average_reward": 0.0,
        "duration": 4.13
    },
    "187": {
        "loss": 0.008,
        "timesteps": 3,
        "average_reward": 0.0,
        "duration": 4.02
    },
    "188": {
        "loss": 0.0089,
        "timesteps": 3,
        "average_reward": 0.0,
        "duration": 3.67
    },
    "189": {
        "loss": 0.0079,
        "timesteps": 3,
        "average_reward": 0.0,
        "duration": 1.72
    },
    "190": {
        "loss": 0.0065,
        "timesteps": 3,
        "average_reward": 0.0,
        "duration": 3.86
    },
    "191": {
        "loss": 0.0063,
        "timesteps": 3,
        "average_reward": 0.0,
        "duration": 4.3
    },
    "192": {
        "loss": 0.0068,
        "timesteps": 3,
        "average_reward": 0.0,
        "duration": 4.23
    },
    "193": {
        "loss": 0.0074,
        "timesteps": 3,
        "average_reward": 0.0,
        "duration": 3.79
    },
    "194": {
        "loss": 0.0064,
        "timesteps": 3,
        "average_reward": 0.0,
        "duration": 3.9
    },
    "195": {
        "loss": 0.0084,
        "timesteps": 3,
        "average_reward": 0.0,
        "duration": 3.71
    },
    "196": {
        "loss": 0.0072,
        "timesteps": 3,
        "average_reward": 0.0,
        "duration": 4.14
    },
    "197": {
        "loss": 0.0063,
        "timesteps": 3,
        "average_reward": 0.0,
        "duration": 3.79
    },
    "198": {
        "loss": 0.0069,
        "timesteps": 3,
        "average_reward": 0.0,
        "duration": 4.17
    },
    "199": {
        "loss": 0.0063,
        "timesteps": 3,
        "average_reward": 0.0,
        "duration": 4.0
    },
    "200": {
        "loss": 0.0077,
        "timesteps": 3,
        "average_reward": 0.0,
        "duration": 4.08
    },
    "201": {
        "loss": 0.0056,
        "timesteps": 3,
        "average_reward": 0.0,
        "duration": 4.16
    },
    "202": {
        "loss": 0.0065,
        "timesteps": 3,
        "average_reward": 0.0,
        "duration": 4.21
    },
    "203": {
        "loss": 0.0055,
        "timesteps": 3,
        "average_reward": 0.0,
        "duration": 4.18
    },
    "204": {
        "loss": 0.0077,
        "timesteps": 3,
        "average_reward": 0.0,
        "duration": 4.19
    },
    "205": {
        "loss": 0.0056,
        "timesteps": 3,
        "average_reward": 0.0,
        "duration": 3.73
    },
    "206": {
        "loss": 0.0066,
        "timesteps": 3,
        "average_reward": 0.0,
        "duration": 4.18
    },
    "207": {
        "loss": 0.0068,
        "timesteps": 3,
        "average_reward": 0.0,
        "duration": 3.77
    },
    "208": {
        "loss": 0.008,
        "timesteps": 3,
        "average_reward": 0.0,
        "duration": 4.06
    },
    "209": {
        "loss": 0.0061,
        "timesteps": 3,
        "average_reward": 0.0,
        "duration": 3.56
    },
    "210": {
        "loss": 0.0069,
        "timesteps": 3,
        "average_reward": 0.0,
        "duration": 4.08
    },
    "211": {
        "loss": 0.0051,
        "timesteps": 3,
        "average_reward": 0.0,
        "duration": 4.15
    },
    "212": {
        "loss": 0.0072,
        "timesteps": 3,
        "average_reward": 0.0,
        "duration": 3.82
    },
    "213": {
        "loss": 0.0057,
        "timesteps": 3,
        "average_reward": 0.0,
        "duration": 3.88
    },
    "214": {
        "loss": 0.0059,
        "timesteps": 3,
        "average_reward": 0.0,
        "duration": 4.26
    },
    "215": {
        "loss": 0.0078,
        "timesteps": 3,
        "average_reward": 0.0,
        "duration": 1.52
    },
    "216": {
        "loss": 0.006,
        "timesteps": 3,
        "average_reward": 0.0,
        "duration": 4.05
    },
    "217": {
        "loss": 0.0089,
        "timesteps": 3,
        "average_reward": 0.0,
        "duration": 3.99
    },
    "218": {
        "loss": 0.003,
        "timesteps": 3,
        "average_reward": 0.0,
        "duration": 4.09
    },
    "219": {
        "loss": 0.0058,
        "timesteps": 3,
        "average_reward": 0.0,
        "duration": 4.36
    },
    "220": {
        "loss": 0.0062,
        "timesteps": 3,
        "average_reward": 0.0,
        "duration": 3.71
    },
    "221": {
        "loss": 0.0084,
        "timesteps": 3,
        "average_reward": 0.0,
        "duration": 4.28
    },
    "222": {
        "loss": 0.0046,
        "timesteps": 3,
        "average_reward": 0.0,
        "duration": 4.42
    },
    "223": {
        "loss": 0.006,
        "timesteps": 3,
        "average_reward": 0.0,
        "duration": 1.45
    },
    "224": {
        "loss": 0.0076,
        "timesteps": 3,
        "average_reward": 0.0,
        "duration": 4.42
    },
    "225": {
        "loss": 0.006,
        "timesteps": 3,
        "average_reward": 0.0,
        "duration": 4.13
    },
    "226": {
        "loss": 0.0071,
        "timesteps": 3,
        "average_reward": 0.0,
        "duration": 4.28
    },
    "227": {
        "loss": 0.0078,
        "timesteps": 3,
        "average_reward": 0.0,
        "duration": 4.08
    },
    "228": {
        "loss": 0.0064,
        "timesteps": 3,
        "average_reward": 0.0,
        "duration": 4.05
    },
    "229": {
        "loss": 0.0088,
        "timesteps": 3,
        "average_reward": 0.0,
        "duration": 3.86
    },
    "230": {
        "loss": 0.0067,
        "timesteps": 3,
        "average_reward": 0.0,
        "duration": 1.71
    },
    "231": {
        "loss": 0.0052,
        "timesteps": 3,
        "average_reward": 0.0,
        "duration": 1.74
    },
    "232": {
        "loss": 0.0069,
        "timesteps": 3,
        "average_reward": 0.0,
        "duration": 3.73
    },
    "233": {
        "loss": 0.0056,
        "timesteps": 3,
        "average_reward": 0.0,
        "duration": 3.97
    },
    "234": {
        "loss": 0.0076,
        "timesteps": 3,
        "average_reward": 0.0,
        "duration": 4.11
    },
    "235": {
        "loss": 0.0063,
        "timesteps": 3,
        "average_reward": 0.0,
        "duration": 3.81
    },
    "236": {
        "loss": 0.0074,
        "timesteps": 4,
        "average_reward": 0.0,
        "duration": 2.12
    },
    "237": {
        "loss": 0.0059,
        "timesteps": 3,
        "average_reward": 0.0,
        "duration": 1.6
    },
    "238": {
        "loss": 0.005,
        "timesteps": 3,
        "average_reward": 0.0,
        "duration": 3.83
    },
    "239": {
        "loss": 0.0064,
        "timesteps": 3,
        "average_reward": 0.0,
        "duration": 3.61
    },
    "240": {
        "loss": 0.0061,
        "timesteps": 3,
        "average_reward": 0.0,
        "duration": 4.15
    },
    "241": {
        "loss": 0.0043,
        "timesteps": 3,
        "average_reward": 0.0,
        "duration": 1.57
    },
    "242": {
        "loss": 0.0078,
        "timesteps": 3,
        "average_reward": 0.0,
        "duration": 3.67
    },
    "243": {
        "loss": 0.006,
        "timesteps": 3,
        "average_reward": 0.0,
        "duration": 3.67
    },
    "244": {
        "loss": 0.0051,
        "timesteps": 3,
        "average_reward": 0.0,
        "duration": 3.83
    },
    "245": {
        "loss": 0.0063,
        "timesteps": 3,
        "average_reward": 0.0,
        "duration": 3.72
    },
    "246": {
        "loss": 0.0061,
        "timesteps": 3,
        "average_reward": 0.0,
        "duration": 1.53
    },
    "247": {
        "loss": 0.0065,
        "timesteps": 3,
        "average_reward": 0.0,
        "duration": 1.66
    },
    "248": {
        "loss": 0.005,
        "timesteps": 3,
        "average_reward": 0.0,
        "duration": 4.02
    },
    "249": {
        "loss": 0.0045,
        "timesteps": 3,
        "average_reward": 0.0,
        "duration": 3.86
    },
    "250": {
        "loss": 0.0051,
        "timesteps": 3,
        "average_reward": 0.0,
        "duration": 4.2
    },
    "251": {
        "loss": 0.0041,
        "timesteps": 3,
        "average_reward": 0.0,
        "duration": 3.94
    },
    "252": {
        "loss": 0.0046,
        "timesteps": 3,
        "average_reward": 0.0,
        "duration": 4.24
    },
    "253": {
        "loss": 0.0071,
        "timesteps": 3,
        "average_reward": 0.0,
        "duration": 3.93
    },
    "254": {
        "loss": 0.0077,
        "timesteps": 3,
        "average_reward": 0.0,
        "duration": 4.21
    },
    "255": {
        "loss": 0.0073,
        "timesteps": 3,
        "average_reward": 0.0,
        "duration": 3.81
    },
    "256": {
        "loss": 0.006,
        "timesteps": 3,
        "average_reward": 0.0,
        "duration": 4.02
    },
    "257": {
        "loss": 0.0067,
        "timesteps": 3,
        "average_reward": 0.0,
        "duration": 3.94
    },
    "258": {
        "loss": 0.0074,
        "timesteps": 3,
        "average_reward": 0.0,
        "duration": 4.04
    },
    "259": {
        "loss": 0.0049,
        "timesteps": 3,
        "average_reward": 0.0,
        "duration": 3.65
    },
    "260": {
        "loss": 0.0064,
        "timesteps": 3,
        "average_reward": 0.0,
        "duration": 3.81
    },
    "261": {
        "loss": 0.0056,
        "timesteps": 3,
        "average_reward": 0.0,
        "duration": 4.09
    },
    "262": {
        "loss": 0.0066,
        "timesteps": 3,
        "average_reward": 0.0,
        "duration": 4.13
    },
    "263": {
        "loss": 0.0084,
        "timesteps": 3,
        "average_reward": 0.0,
        "duration": 4.07
    },
    "264": {
        "loss": 0.0071,
        "timesteps": 3,
        "average_reward": 0.0,
        "duration": 4.24
    },
    "265": {
        "loss": 0.0055,
        "timesteps": 3,
        "average_reward": 0.0,
        "duration": 4.0
    },
    "266": {
        "loss": 0.0072,
        "timesteps": 3,
        "average_reward": 0.0,
        "duration": 3.62
    },
    "267": {
        "loss": 0.0073,
        "timesteps": 3,
        "average_reward": 0.0,
        "duration": 4.21
    },
    "268": {
        "loss": 0.0072,
        "timesteps": 3,
        "average_reward": 0.0,
        "duration": 4.1
    },
    "269": {
        "loss": 0.0075,
        "timesteps": 3,
        "average_reward": 0.0,
        "duration": 3.45
    },
    "270": {
        "loss": 0.007,
        "timesteps": 3,
        "average_reward": 0.0,
        "duration": 3.75
    },
    "271": {
        "loss": 0.0079,
        "timesteps": 3,
        "average_reward": 0.0,
        "duration": 3.72
    },
    "272": {
        "loss": 0.0084,
        "timesteps": 3,
        "average_reward": 0.0,
        "duration": 4.06
    },
    "273": {
        "loss": 0.006,
        "timesteps": 3,
        "average_reward": 0.0,
        "duration": 4.12
    },
    "274": {
        "loss": 0.0078,
        "timesteps": 3,
        "average_reward": 0.0,
        "duration": 4.03
    },
    "275": {
        "loss": 0.0053,
        "timesteps": 3,
        "average_reward": 0.0,
        "duration": 3.73
    },
    "276": {
        "loss": 0.0073,
        "timesteps": 3,
        "average_reward": 0.0,
        "duration": 3.75
    },
    "277": {
        "loss": 0.0066,
        "timesteps": 3,
        "average_reward": 0.0,
        "duration": 4.06
    },
    "278": {
        "loss": 0.0054,
        "timesteps": 3,
        "average_reward": 0.0,
        "duration": 3.62
    },
    "279": {
        "loss": 0.0061,
        "timesteps": 3,
        "average_reward": 0.0,
        "duration": 4.06
    },
    "280": {
        "loss": 0.0059,
        "timesteps": 3,
        "average_reward": 0.0,
        "duration": 4.08
    },
    "281": {
        "loss": 0.0051,
        "timesteps": 3,
        "average_reward": 0.0,
        "duration": 3.97
    },
    "282": {
        "loss": 0.008,
        "timesteps": 3,
        "average_reward": 0.0,
        "duration": 4.03
    },
    "283": {
        "loss": 0.0092,
        "timesteps": 3,
        "average_reward": 0.0,
        "duration": 4.24
    },
    "284": {
        "loss": 0.0058,
        "timesteps": 3,
        "average_reward": 0.0,
        "duration": 4.18
    },
    "285": {
        "loss": 0.0057,
        "timesteps": 3,
        "average_reward": 0.0,
        "duration": 3.86
    },
    "286": {
        "loss": 0.0068,
        "timesteps": 3,
        "average_reward": 0.0,
        "duration": 4.05
    },
    "287": {
        "loss": 0.0063,
        "timesteps": 3,
        "average_reward": 0.0,
        "duration": 4.2
    },
    "288": {
        "loss": 0.0057,
        "timesteps": 3,
        "average_reward": 0.0,
        "duration": 3.57
    },
    "289": {
        "loss": 0.0064,
        "timesteps": 3,
        "average_reward": 0.0,
        "duration": 4.19
    },
    "290": {
        "loss": 0.0083,
        "timesteps": 3,
        "average_reward": 0.0,
        "duration": 4.0
    },
    "291": {
        "loss": 0.0088,
        "timesteps": 3,
        "average_reward": 0.0,
        "duration": 3.75
    },
    "292": {
        "loss": 0.0047,
        "timesteps": 3,
        "average_reward": 0.0,
        "duration": 4.01
    },
    "293": {
        "loss": 0.007,
        "timesteps": 3,
        "average_reward": 0.0,
        "duration": 4.14
    },
    "294": {
        "loss": 0.006,
        "timesteps": 3,
        "average_reward": 0.0,
        "duration": 4.24
    },
    "295": {
        "loss": 0.0055,
        "timesteps": 3,
        "average_reward": 0.0,
        "duration": 4.0
    },
    "296": {
        "loss": 0.0075,
        "timesteps": 3,
        "average_reward": 0.0,
        "duration": 1.65
    },
    "297": {
        "loss": 0.0054,
        "timesteps": 3,
        "average_reward": 0.0,
        "duration": 3.52
    },
    "298": {
        "loss": 0.0056,
        "timesteps": 3,
        "average_reward": 0.0,
        "duration": 3.91
    },
    "299": {
        "loss": 0.0057,
        "timesteps": 3,
        "average_reward": 0.0,
        "duration": 1.55
    },
    "300": {
        "loss": 0.005,
        "timesteps": 3,
        "average_reward": 0.0,
        "duration": 3.83
    }
}